chronology/Timer.py
chronology/YearMonth.py
chronology/YearQuarter.py
chronology/__init__.py
chronology/add_time.py
chronology/elapsed_time.py
chronology/get_month.py
chronology/get_time.py
chronology/remove_non_alphanumeric.py
chronology/to_date_part.py
chronology/to_quarter.py
chronology/numbers/FlexibleNumber.py
chronology/numbers/NumberPart.py
chronology/numbers/__init__.py
sumer/Timer.py
sumer/YearMonth.py
sumer/YearQuarter.py
sumer/__init__.py
sumer/add_time.py
sumer/elapsed_time.py
sumer/get_month.py
sumer/get_time.py
sumer/remove_non_alphanumeric.py
sumer/to_date_part.py
sumer/to_quarter.py
sumer/numbers/FlexibleNumber.py
sumer/numbers/NumberPart.py
sumer/numbers/__init__.py
chronology-1.1.dist-info/LICENSE
chronology-1.1.dist-info/METADATA
chronology-1.1.dist-info/WHEEL
chronology-1.1.dist-info/top_level.txt
chronology-1.1.dist-info/RECORD
